[
    {
        "nameAndSurname": "No\u00e9 Perez",
        "username": "No\u00e9Pere",
        "email": "No\u00e9Pere@example.com"
    },
    {
        "nameAndSurname": "Pastor Castro",
        "username": "PastCastr",
        "email": "PastCastr@example.com"
    },
    {
        "nameAndSurname": "Eust\u00e0quia Marquez",
        "username": "EuMarque",
        "email": "EuMarque@example.com"
    },
    {
        "nameAndSurname": "Kai Vila",
        "username": "KaiVila",
        "email": "KaiVila@example.com"
    },
    {
        "nameAndSurname": "Valeri\u00e0 Mendez",
        "username": "ValMend",
        "email": "ValMend@example.com"
    },
    {
        "nameAndSurname": "Gast\u00f3 Ruiz",
        "username": "GasRuiz",
        "email": "GasRuiz@example.com"
    },
    {
        "nameAndSurname": "Aventina Sanchez",
        "username": "AvenSan",
        "email": "AvenSan@example.com"
    },
    {
        "nameAndSurname": "Beatriu Lozano",
        "username": "BeaLoz",
        "email": "BeaLoz@example.com"
    },
    {
        "nameAndSurname": "Amat Iba\u00f1ez",
        "username": "AmatIb",
        "email": "AmatIb@example.com"
    },
    {
        "nameAndSurname": "Prisca Gutierrez",
        "username": "PriGutie",
        "email": "PriGutie@example.com"
    },
    {
        "nameAndSurname": "Nic\u00e0sia Cortes",
        "username": "Nic\u00e0Cor",
        "email": "Nic\u00e0Cor@example.com"
    },
    {
        "nameAndSurname": " Mu\u00f1oz",
        "username": "Mu\u00f1",
        "email": "Mu\u00f1@example.com"
    },
    {
        "nameAndSurname": "C\u00e9sar Parra",
        "username": "C\u00e9Parr",
        "email": "C\u00e9Parr@example.com"
    },
    {
        "nameAndSurname": "Alpini+a Diaz",
        "username": "AlpinDia",
        "email": "AlpinDia@example.com"
    },
    {
        "nameAndSurname": "Cora Lopez",
        "username": "CorLopez",
        "email": "CorLopez@example.com"
    },
    {
        "nameAndSurname": "Eufemi Costa",
        "username": "EufCost",
        "email": "EufCost@example.com"
    },
    {
        "nameAndSurname": "Pelai Segura",
        "username": "PelaSe",
        "email": "PelaSe@example.com"
    },
    {
        "nameAndSurname": "Abas Herrera",
        "username": "AbHerrer",
        "email": "AbHerrer@example.com"
    },
    {
        "nameAndSurname": "Queralt Ramos",
        "username": "QueralRa",
        "email": "QueralRa@example.com"
    },
    {
        "nameAndSurname": "Gil Suarez",
        "username": "GiSu",
        "email": "GiSu@example.com"
    },
    {
        "nameAndSurname": "Clet Dominguez",
        "username": "CletDominguez",
        "email": "CletDominguez@example.com"
    },
    {
        "nameAndSurname": "Fela Ramirez",
        "username": "FelRam",
        "email": "FelRam@example.com"
    },
    {
        "nameAndSurname": "Amarant Garrido",
        "username": "AmarGarrido",
        "email": "AmarGarrido@example.com"
    },
    {
        "nameAndSurname": "Magina Cortes",
        "username": "MagCorte",
        "email": "MagCorte@example.com"
    },
    {
        "nameAndSurname": "Mariona Perez",
        "username": "MariPer",
        "email": "MariPer@example.com"
    },
    {
        "nameAndSurname": "Melit\u00f3 Ortega",
        "username": "Melit\u00f3Orteg",
        "email": "Melit\u00f3Orteg@example.com"
    },
    {
        "nameAndSurname": "G\u00fadula Pascual",
        "username": "G\u00faduPas",
        "email": "G\u00faduPas@example.com"
    },
    {
        "nameAndSurname": "Generosa Cabrera",
        "username": "GenerosCabr",
        "email": "GenerosCabr@example.com"
    },
    {
        "nameAndSurname": "Porfiri Martin",
        "username": "PorfiriMar",
        "email": "PorfiriMar@example.com"
    },
    {
        "nameAndSurname": "Gala Moreno",
        "username": "GalMoreno",
        "email": "GalMoreno@example.com"
    },
    {
        "nameAndSurname": "Agat\u00e0ngel Romero",
        "username": "AgatRomer",
        "email": "AgatRomer@example.com"
    },
    {
        "nameAndSurname": "Donata Rojas",
        "username": "DonaRoja",
        "email": "DonaRoja@example.com"
    },
    {
        "nameAndSurname": "Climent Aguilar",
        "username": "CliAgui",
        "email": "CliAgui@example.com"
    },
    {
        "nameAndSurname": "Mari\u00e0 Moreno",
        "username": "MarMore",
        "email": "MarMore@example.com"
    },
    {
        "nameAndSurname": "Abili Martin",
        "username": "AbilMart",
        "email": "AbilMart@example.com"
    },
    {
        "nameAndSurname": "Calixt Gutierrez",
        "username": "CaliGutierr",
        "email": "CaliGutierr@example.com"
    },
    {
        "nameAndSurname": "Primitiva Rojas",
        "username": "PrimitivRo",
        "email": "PrimitivRo@example.com"
    },
    {
        "nameAndSurname": "\u00c0niceta Reyes",
        "username": "\u00c0niRe",
        "email": "\u00c0niRe@example.com"
    },
    {
        "nameAndSurname": "Zenofre Torres",
        "username": "ZenoTorre",
        "email": "ZenoTorre@example.com"
    },
    {
        "nameAndSurname": "Maxim\u00ed Martinez",
        "username": "MaxMartinez",
        "email": "MaxMartinez@example.com"
    },
    {
        "nameAndSurname": "Teia Parra",
        "username": "TeiPar",
        "email": "TeiPar@example.com"
    },
    {
        "nameAndSurname": "Virgili Castro",
        "username": "VirCa",
        "email": "VirCa@example.com"
    },
    {
        "nameAndSurname": "Gisela Lozano",
        "username": "GisLo",
        "email": "GisLo@example.com"
    },
    {
        "nameAndSurname": "Secund\u00ed Vila",
        "username": "SecuVila",
        "email": "SecuVila@example.com"
    },
    {
        "nameAndSurname": "Roberta Torres",
        "username": "RobeTorr",
        "email": "RobeTorr@example.com"
    },
    {
        "nameAndSurname": "Jordana Puig",
        "username": "JordanaPuig",
        "email": "JordanaPuig@example.com"
    },
    {
        "nameAndSurname": "Ezequiel Herrera",
        "username": "EzequielHerrer",
        "email": "EzequielHerrer@example.com"
    },
    {
        "nameAndSurname": "Andrea Fuentes",
        "username": "AndreaFuentes",
        "email": "AndreaFuentes@example.com"
    },
    {
        "nameAndSurname": "Zen\u00f3 Castro",
        "username": "ZenCastr",
        "email": "ZenCastr@example.com"
    },
    {
        "nameAndSurname": "Heliodora Parra",
        "username": "HelioPar",
        "email": "HelioPar@example.com"
    },
    {
        "nameAndSurname": "Chima Carmona",
        "username": "ChimaCarmon",
        "email": "ChimaCarmon@example.com"
    },
    {
        "nameAndSurname": "Pr\u00e0xedes Cabrera",
        "username": "Pr\u00e0xCa",
        "email": "Pr\u00e0xCa@example.com"
    },
    {
        "nameAndSurname": "Nura Leon",
        "username": "NuraLeo",
        "email": "NuraLeo@example.com"
    },
    {
        "nameAndSurname": "Generosa Soler",
        "username": "GenerosSo",
        "email": "GenerosSo@example.com"
    },
    {
        "nameAndSurname": "\u00c0uria Vargas",
        "username": "\u00c0uVarga",
        "email": "\u00c0uVarga@example.com"
    },
    {
        "nameAndSurname": "Homer Rodriguez",
        "username": "HomeRodriguez",
        "email": "HomeRodriguez@example.com"
    },
    {
        "nameAndSurname": "Hermione Rodriguez",
        "username": "HermiRodri",
        "email": "HermiRodri@example.com"
    },
    {
        "nameAndSurname": "Antoni Gil",
        "username": "AntGil",
        "email": "AntGil@example.com"
    },
    {
        "nameAndSurname": "Erasme Serra",
        "username": "ErasmSerr",
        "email": "ErasmSerr@example.com"
    },
    {
        "nameAndSurname": "J\u00falia Iglesias",
        "username": "J\u00falIgle",
        "email": "J\u00falIgle@example.com"
    },
    {
        "nameAndSurname": "Crescenci Fuentes",
        "username": "CresceFu",
        "email": "CresceFu@example.com"
    },
    {
        "nameAndSurname": "Herm\u00ednia Rubio",
        "username": "Herm\u00edRub",
        "email": "Herm\u00edRub@example.com"
    },
    {
        "nameAndSurname": "Z\u00f2sima Carrasco",
        "username": "Z\u00f2sCarras",
        "email": "Z\u00f2sCarras@example.com"
    },
    {
        "nameAndSurname": "Liberata Carmona",
        "username": "LiberatCarmona",
        "email": "LiberatCarmona@example.com"
    },
    {
        "nameAndSurname": "Ces\u00e0reu Iglesias",
        "username": "CesIglesia",
        "email": "CesIglesia@example.com"
    },
    {
        "nameAndSurname": "Abdon Mora",
        "username": "AbMor",
        "email": "AbMor@example.com"
    },
    {
        "nameAndSurname": "Yanira Herrera",
        "username": "YanirHerrera",
        "email": "YanirHerrera@example.com"
    },
    {
        "nameAndSurname": "Regina Cabrera",
        "username": "RegiCabrer",
        "email": "RegiCabrer@example.com"
    },
    {
        "nameAndSurname": "Ala\u00efs Casas",
        "username": "Ala\u00efsCa",
        "email": "Ala\u00efsCa@example.com"
    },
    {
        "nameAndSurname": "Afrod\u00edsia Marti",
        "username": "AfMar",
        "email": "AfMar@example.com"
    },
    {
        "nameAndSurname": "Ia Rodriguez",
        "username": "IaRodr",
        "email": "IaRodr@example.com"
    },
    {
        "nameAndSurname": "Humberta Parra",
        "username": "HumbertParr",
        "email": "HumbertParr@example.com"
    },
    {
        "nameAndSurname": "Petra Romero",
        "username": "PetrRome",
        "email": "PetrRome@example.com"
    },
    {
        "nameAndSurname": "Heliodora Font",
        "username": "HeFont",
        "email": "HeFont@example.com"
    },
    {
        "nameAndSurname": "Mateu Ferrer",
        "username": "MaFer",
        "email": "MaFer@example.com"
    },
    {
        "nameAndSurname": "Sebasti\u00e0 Santos",
        "username": "SebasSa",
        "email": "SebasSa@example.com"
    },
    {
        "nameAndSurname": "Uria Gil",
        "username": "UriaGi",
        "email": "UriaGi@example.com"
    },
    {
        "nameAndSurname": "Priscila Pascual",
        "username": "PrisciPas",
        "email": "PrisciPas@example.com"
    },
    {
        "nameAndSurname": "Dar\u00ed Roig",
        "username": "Dar\u00edRo",
        "email": "Dar\u00edRo@example.com"
    },
    {
        "nameAndSurname": "Ven\u00e0ncia Mendez",
        "username": "Ven\u00e0nMende",
        "email": "Ven\u00e0nMende@example.com"
    },
    {
        "nameAndSurname": "Virg\u00ednia Molina",
        "username": "Virg\u00edniMolin",
        "email": "Virg\u00edniMolin@example.com"
    },
    {
        "nameAndSurname": "Teodomir Calvo",
        "username": "TeodomCalv",
        "email": "TeodomCalv@example.com"
    },
    {
        "nameAndSurname": "Lluca Costa",
        "username": "LluCo",
        "email": "LluCo@example.com"
    },
    {
        "nameAndSurname": "Noel Mora",
        "username": "NoMora",
        "email": "NoMora@example.com"
    },
    {
        "nameAndSurname": "Prisci\u00e0 Guerrero",
        "username": "PriscGuer",
        "email": "PriscGuer@example.com"
    },
    {
        "nameAndSurname": "Melquiades Rovira",
        "username": "MelquiadesRovi",
        "email": "MelquiadesRovi@example.com"
    },
    {
        "nameAndSurname": "Elvira Carmona",
        "username": "ElvCarmo",
        "email": "ElvCarmo@example.com"
    },
    {
        "nameAndSurname": "Pepa Campos",
        "username": "PepCampo",
        "email": "PepCampo@example.com"
    },
    {
        "nameAndSurname": "Fulbert Serrano",
        "username": "FulbertSerr",
        "email": "FulbertSerr@example.com"
    },
    {
        "nameAndSurname": "Calixt Costa",
        "username": "CalixtCo",
        "email": "CalixtCo@example.com"
    },
    {
        "nameAndSurname": "Casta Cano",
        "username": "CasCa",
        "email": "CasCa@example.com"
    },
    {
        "nameAndSurname": "Radegundis Cabrera",
        "username": "RadeCabrera",
        "email": "RadeCabrera@example.com"
    },
    {
        "nameAndSurname": "Apoloni Moya",
        "username": "ApoMoya",
        "email": "ApoMoya@example.com"
    },
    {
        "nameAndSurname": "Clem\u00e8ncia Sole",
        "username": "Clem\u00e8nciaSo",
        "email": "Clem\u00e8nciaSo@example.com"
    },
    {
        "nameAndSurname": "Nina Sole",
        "username": "NinSole",
        "email": "NinSole@example.com"
    },
    {
        "nameAndSurname": "Paulina Aguilera",
        "username": "PauAgu",
        "email": "PauAgu@example.com"
    },
    {
        "nameAndSurname": "Llura Roig",
        "username": "LluRo",
        "email": "LluRo@example.com"
    },
    {
        "nameAndSurname": "Marceliana Ramos",
        "username": "MarcelianaRa",
        "email": "MarcelianaRa@example.com"
    },
    {
        "nameAndSurname": "Alina Moya",
        "username": "AlMo",
        "email": "AlMo@example.com"
    },
    {
        "nameAndSurname": "Baltasara Flores",
        "username": "BaltasaraFlores",
        "email": "BaltasaraFlores@example.com"
    }
]
